PrimeAPIClient/__init__.py
PrimeAPIClient/api_interface.py
PrimeAPIClient-0.0.1.dist-info/LICENSE
PrimeAPIClient-0.0.1.dist-info/METADATA
PrimeAPIClient-0.0.1.dist-info/WHEEL
PrimeAPIClient-0.0.1.dist-info/top_level.txt
PrimeAPIClient-0.0.1.dist-info/RECORD
